[{"region":"Acacia Gardens","mu_R":-0.0367,"sigma_R":0.0269,"mu_L":5.9955,"sigma_L":0.4491,"n":45},{"region":"Annandale (NSW)","mu_R":0.082,"sigma_R":0.0509,"mu_L":5.2012,"sigma_L":0.4313,"n":112},{"region":"Armidale Surrounds - South","mu_R":0.0631,"sigma_R":0.0481,"mu_L":5.19,"sigma_L":0.5253,"n":56},{"region":"Arncliffe - Bardwell Valley","mu_R":0.0313,"sigma_R":0.0326,"mu_L":6.0801,"sigma_L":0.2974,"n":80},{"region":"Artarmon","mu_R":0.14,"sigma_R":0.0297,"mu_L":6.3966,"sigma_L":0.3219,"n":43},{"region":"Ashcroft - Busby - Miller","mu_R":-0.0807,"sigma_R":0.0161,"mu_L":6.4035,"sigma_L":0.1393,"n":155},{"region":"Ashfield - North","mu_R":0.0714,"sigma_R":0.0429,"mu_L":6.1047,"sigma_L":0.4557,"n":84},{"region":"Asquith - Mount Colah","mu_R":0.0096,"sigma_R":0.0291,"mu_L":6.7128,"sigma_L":0.3483,"n":239},{"region":"Auburn - Central","mu_R":-0.0154,"sigma_R":0.0427,"mu_L":6.2262,"sigma_L":0.3487,"n":138},{"region":"Austral - Greendale","mu_R":0.101,"sigma_R":0.0678,"mu_L":9.6032,"sigma_L":1.0136,"n":72},{"region":"Avalon - Palm Beach","mu_R":0.0779,"sigma_R":0.0314,"mu_L":6.5688,"sigma_L":0.2995,"n":62},{"region":"Balgowlah - Clontarf - Seaforth","mu_R":0.1319,"sigma_R":0.0488,"mu_L":6.4111,"sigma_L":0.3436,"n":241},{"region":"Balmain","mu_R":0.141,"sigma_R":0.0684,"mu_L":5.2633,"sigma_L":0.5112,"n":206},{"region":"Bankstown - North","mu_R":-0.017,"sigma_R":0.0403,"mu_L":6.2373,"sigma_L":0.405,"n":94},{"region":"Bargo","mu_R":-0.0597,"sigma_R":0.0443,"mu_L":7.8536,"sigma_L":1.4953,"n":72},{"region":"Bass Hill - Georges Hall","mu_R":-0.0254,"sigma_R":0.0311,"mu_L":6.2953,"sigma_L":0.3605,"n":245},{"region":"Baulkham Hills (West) - Bella Vista","mu_R":0.0692,"sigma_R":0.0369,"mu_L":6.4167,"sigma_L":0.3767,"n":76},{"region":"Baulkham Hills - East","mu_R":0.0159,"sigma_R":0.0227,"mu_L":6.6075,"sigma_L":0.2709,"n":352},{"region":"Bayview - Elanora Heights","mu_R":0.0875,"sigma_R":0.0407,"mu_L":7.3182,"sigma_L":1.122,"n":50},{"region":"Beacon Hill - Narraweena","mu_R":0.0536,"sigma_R":0.0234,"mu_L":6.4086,"sigma_L":0.2448,"n":132},{"region":"Bega-Eden Hinterland","mu_R":-0.0672,"sigma_R":0.038,"mu_L":6.5672,"sigma_L":0.6713,"n":125},{"region":"Bellevue Hill","mu_R":0.256,"sigma_R":0.0695,"mu_L":6.5584,"sigma_L":0.3854,"n":97},{"region":"Belmore - Belfield","mu_R":0.0263,"sigma_R":0.0358,"mu_L":6.2116,"sigma_L":0.2789,"n":102},{"region":"Belrose","mu_R":0.0658,"sigma_R":0.0274,"mu_L":6.6448,"sigma_L":0.5371,"n":75},{"region":"Berala","mu_R":-0.0122,"sigma_R":0.0329,"mu_L":6.1638,"sigma_L":0.303,"n":47},{"region":"Berowra - Brooklyn - Cowan","mu_R":-0.0095,"sigma_R":0.0275,"mu_L":6.668,"sigma_L":0.2851,"n":152},{"region":"Bexley - North","mu_R":0.0284,"sigma_R":0.0358,"mu_L":6.1658,"sigma_L":0.3279,"n":129},{"region":"Bidwill - Hebersham - Emerton","mu_R":-0.1111,"sigma_R":0.0217,"mu_L":6.4112,"sigma_L":0.1415,"n":183},{"region":"Bilpin - Colo - St Albans","mu_R":-0.0208,"sigma_R":0.0384,"mu_L":9.6951,"sigma_L":1.9267,"n":38},{"region":"Blacktown (East) - Kings Park","mu_R":-0.0558,"sigma_R":0.0285,"mu_L":6.1923,"sigma_L":0.5015,"n":619},{"region":"Blacktown (North) - Marayong","mu_R":-0.0646,"sigma_R":0.0223,"mu_L":6.4273,"sigma_L":0.1867,"n":97},{"region":"Bondi - Tamarama - Bronte","mu_R":0.1987,"sigma_R":0.0626,"mu_L":5.7844,"sigma_L":0.4401,"n":139},{"region":"Bondi Beach - North Bondi","mu_R":0.1849,"sigma_R":0.0541,"mu_L":5.7356,"sigma_L":0.3403,"n":105},{"region":"Bondi Junction - Waverly","mu_R":0.1455,"sigma_R":0.0534,"mu_L":5.3381,"sigma_L":0.488,"n":127},{"region":"Bonnells Bay - Silverwater","mu_R":-0.0004,"sigma_R":0.0225,"mu_L":6.4929,"sigma_L":0.0864,"n":4},{"region":"Bonnyrigg Heights - Bonnyrigg","mu_R":-0.0484,"sigma_R":0.0316,"mu_L":6.324,"sigma_L":0.2919,"n":100},{"region":"Bossley Park - Abbotsbury","mu_R":-0.0284,"sigma_R":0.0309,"mu_L":6.3936,"sigma_L":0.2033,"n":139},{"region":"Botany","mu_R":0.0641,"sigma_R":0.0297,"mu_L":5.7448,"sigma_L":0.6157,"n":72},{"region":"Box Hill - Nelson","mu_R":0.0413,"sigma_R":0.1462,"mu_L":7.8268,"sigma_L":2.0739,"n":50},{"region":"Bradbury - Wedderburn","mu_R":-0.0938,"sigma_R":0.0273,"mu_L":6.373,"sigma_L":0.6299,"n":249},{"region":"Burwood (NSW)","mu_R":0.1083,"sigma_R":0.0521,"mu_L":6.2629,"sigma_L":0.429,"n":59},{"region":"Cabramatta - Lansvale","mu_R":-0.0398,"sigma_R":0.033,"mu_L":6.4573,"sigma_L":0.2844,"n":95},{"region":"Cabramatta West - Mount Pritchard","mu_R":-0.0478,"sigma_R":0.0348,"mu_L":6.4333,"sigma_L":0.3003,"n":174},{"region":"Calga - Kulnura","mu_R":-0.0446,"sigma_R":0.0289,"mu_L":6.727,"sigma_L":0.0108,"n":2},{"region":"Cambridge Park","mu_R":-0.0802,"sigma_R":0.02,"mu_L":6.4953,"sigma_L":0.1831,"n":242},{"region":"Camden - Ellis Lane","mu_R":-0.047,"sigma_R":0.0385,"mu_L":6.6477,"sigma_L":0.4477,"n":152},{"region":"Campbelltown - Woodbine","mu_R":-0.079,"sigma_R":0.028,"mu_L":6.3614,"sigma_L":0.2819,"n":242},{"region":"Camperdown - Darlington","mu_R":0.0798,"sigma_R":0.0524,"mu_L":4.9781,"sigma_L":0.3268,"n":39},{"region":"Campsie - North","mu_R":0.0348,"sigma_R":0.0356,"mu_L":6.0199,"sigma_L":0.3581,"n":42},{"region":"Canley Vale - Canley Heights","mu_R":-0.0386,"sigma_R":0.0283,"mu_L":6.202,"sigma_L":0.4772,"n":170},{"region":"Canterbury (North) - Ashbury","mu_R":0.0627,"sigma_R":0.0262,"mu_L":6.1063,"sigma_L":0.2741,"n":49},{"region":"Canterbury - South","mu_R":0.0419,"sigma_R":0.0307,"mu_L":6.1504,"sigma_L":0.3666,"n":36},{"region":"Caringbah","mu_R":0.039,"sigma_R":0.0298,"mu_L":6.483,"sigma_L":0.3072,"n":58},{"region":"Caringbah South","mu_R":0.0675,"sigma_R":0.0354,"mu_L":6.5191,"sigma_L":0.3526,"n":110},{"region":"Carlingford - West","mu_R":0.0463,"sigma_R":0.0336,"mu_L":6.6566,"sigma_L":0.3198,"n":186},{"region":"Castle Cove - Northbridge","mu_R":0.1463,"sigma_R":0.0448,"mu_L":6.4801,"sigma_L":0.2423,"n":82},{"region":"Castle Hill - North","mu_R":0.0553,"sigma_R":0.0307,"mu_L":6.6504,"sigma_L":0.2933,"n":384},{"region":"Casula","mu_R":-0.0412,"sigma_R":0.0358,"mu_L":6.3594,"sigma_L":0.464,"n":162},{"region":"Cecil Hills","mu_R":-0.006,"sigma_R":0.0392,"mu_L":6.3691,"sigma_L":0.2946,"n":67},{"region":"Chatswood (West) - Lane Cove North","mu_R":0.1034,"sigma_R":0.0364,"mu_L":6.3756,"sigma_L":0.4905,"n":54},{"region":"Chatswood - East","mu_R":0.1434,"sigma_R":0.0464,"mu_L":6.3657,"sigma_L":0.3186,"n":118},{"region":"Cherrybrook","mu_R":0.0523,"sigma_R":0.0244,"mu_L":6.5913,"sigma_L":0.3484,"n":188},{"region":"Chester Hill - Sefton","mu_R":-0.031,"sigma_R":0.0195,"mu_L":6.2985,"sigma_L":0.2607,"n":171},{"region":"Chippendale","mu_R":0.1167,"sigma_R":0.0697,"mu_L":4.8803,"sigma_L":0.3995,"n":8},{"region":"Chipping Norton - Moorebank","mu_R":-0.0166,"sigma_R":0.0239,"mu_L":6.2026,"sigma_L":0.3897,"n":275},{"region":"Chullora","mu_R":0.0104,"sigma_R":0.0563,"mu_L":5.8822,"sigma_L":0.4048,"n":3},{"region":"Claymore - Eagle Vale - Raby","mu_R":-0.0848,"sigma_R":0.0235,"mu_L":6.4113,"sigma_L":0.2696,"n":251},{"region":"Cobbitty - Bringelly","mu_R":-0.0434,"sigma_R":0.0247,"mu_L":6.4599,"sigma_L":1.1659,"n":56},{"region":"Collaroy - Collaroy Plateau","mu_R":0.1006,"sigma_R":0.056,"mu_L":6.3401,"sigma_L":0.3364,"n":118},{"region":"Colyton - Oxley Park","mu_R":-0.0786,"sigma_R":0.0265,"mu_L":6.4664,"sigma_L":0.2222,"n":150},{"region":"Concord - Mortlake - Cabarita","mu_R":0.117,"sigma_R":0.0465,"mu_L":6.1729,"sigma_L":0.3409,"n":143},{"region":"Concord West - North Strathfield","mu_R":0.0874,"sigma_R":0.0378,"mu_L":6.2605,"sigma_L":0.4338,"n":73},{"region":"Condell Park","mu_R":-0.0122,"sigma_R":0.0365,"mu_L":6.313,"sigma_L":0.4014,"n":112},{"region":"Coogee - Clovelly","mu_R":0.1847,"sigma_R":0.0509,"mu_L":5.8804,"sigma_L":0.3555,"n":101},{"region":"Cranebrook - Castlereagh","mu_R":-0.0712,"sigma_R":0.0311,"mu_L":6.4454,"sigma_L":0.7646,"n":210},{"region":"Cremorne - Cammeray","mu_R":0.156,"sigma_R":0.0526,"mu_L":6.0163,"sigma_L":0.4292,"n":87},{"region":"Cromer","mu_R":0.0586,"sigma_R":0.0259,"mu_L":6.3773,"sigma_L":0.3597,"n":93},{"region":"Cronulla - Kurnell - Bundeena","mu_R":0.101,"sigma_R":0.0374,"mu_L":6.3405,"sigma_L":0.3007,"n":54},{"region":"Crows Nest - Waverton","mu_R":0.1293,"sigma_R":0.0454,"mu_L":5.6154,"sigma_L":0.4727,"n":49},{"region":"Croydon","mu_R":0.0765,"sigma_R":0.0404,"mu_L":6.0761,"sigma_L":0.4035,"n":68},{"region":"Croydon Park - Enfield","mu_R":0.0498,"sigma_R":0.0393,"mu_L":6.122,"sigma_L":0.3182,"n":92},{"region":"Currans Hill","mu_R":-0.081,"sigma_R":0.019,"mu_L":6.2345,"sigma_L":0.287,"n":88},{"region":"Darlinghurst","mu_R":0.1329,"sigma_R":0.0817,"mu_L":4.7179,"sigma_L":0.6552,"n":60},{"region":"Dee Why (South) - North Curl Curl","mu_R":0.1267,"sigma_R":0.0515,"mu_L":6.3402,"sigma_L":0.2749,"n":42},{"region":"Dee Why - North","mu_R":0.0898,"sigma_R":0.0381,"mu_L":6.3552,"sigma_L":0.2926,"n":49},{"region":"Denham Court - Bardia","mu_R":-0.0802,"sigma_R":0.0424,"mu_L":5.5946,"sigma_L":0.8423,"n":196},{"region":"Denistone","mu_R":0.0658,"sigma_R":0.0301,"mu_L":6.5387,"sigma_L":0.2482,"n":80},{"region":"Doonside - Woodcroft","mu_R":-0.0625,"sigma_R":0.0333,"mu_L":6.1962,"sigma_L":0.4528,"n":181},{"region":"Double Bay - Darling Point","mu_R":0.2393,"sigma_R":0.0745,"mu_L":5.8576,"sigma_L":0.5903,"n":68},{"region":"Douglas Park - Appin","mu_R":-0.0272,"sigma_R":0.0455,"mu_L":7.7012,"sigma_L":1.7299,"n":113},{"region":"Dover Heights","mu_R":0.1982,"sigma_R":0.0434,"mu_L":6.1151,"sigma_L":0.3482,"n":51},{"region":"Drummoyne - Rodd Point","mu_R":0.1248,"sigma_R":0.0557,"mu_L":5.9886,"sigma_L":0.401,"n":131},{"region":"Dulwich Hill - Lewisham","mu_R":0.0593,"sigma_R":0.0324,"mu_L":5.6345,"sigma_L":0.4018,"n":99},{"region":"Dungog","mu_R":0.0811,"sigma_R":0.0459,"mu_L":5.7438,"sigma_L":0.551,"n":38},{"region":"Dural - Kenthurst - Wisemans Ferry","mu_R":0.0637,"sigma_R":0.0452,"mu_L":8.8475,"sigma_L":1.707,"n":225},{"region":"Earlwood","mu_R":0.0599,"sigma_R":0.0413,"mu_L":6.1665,"sigma_L":0.3824,"n":144},{"region":"Eastlakes","mu_R":0.0603,"sigma_R":0.0239,"mu_L":5.8585,"sigma_L":0.3908,"n":18},{"region":"Eastwood","mu_R":0.0828,"sigma_R":0.0274,"mu_L":6.5376,"sigma_L":0.3693,"n":138},{"region":"Edensor Park","mu_R":-0.0323,"sigma_R":0.0376,"mu_L":6.4328,"sigma_L":0.334,"n":72},{"region":"Edmondson Park","mu_R":-0.0178,"sigma_R":0.0882,"mu_L":6.4488,"sigma_L":1.3516,"n":81},{"region":"Elderslie - Narellan","mu_R":-0.0606,"sigma_R":0.0216,"mu_L":6.3073,"sigma_L":0.3669,"n":187},{"region":"Emu Plains - Leonay","mu_R":-0.0531,"sigma_R":0.0303,"mu_L":6.5347,"sigma_L":0.2149,"n":163},{"region":"Engadine","mu_R":-0.0087,"sigma_R":0.0353,"mu_L":6.517,"sigma_L":0.2351,"n":64},{"region":"Epping (East) - North Epping","mu_R":0.0617,"sigma_R":0.0266,"mu_L":6.6175,"sigma_L":0.2895,"n":54},{"region":"Epping (NSW) - West","mu_R":0.0861,"sigma_R":0.0331,"mu_L":6.6486,"sigma_L":0.3868,"n":177},{"region":"Ermington - Rydalmere","mu_R":0.0231,"sigma_R":0.0279,"mu_L":6.3257,"sigma_L":0.3828,"n":219},{"region":"Erskine Park","mu_R":-0.0516,"sigma_R":0.0232,"mu_L":6.5313,"sigma_L":0.347,"n":63},{"region":"Erskineville - Alexandria","mu_R":0.0707,"sigma_R":0.0503,"mu_L":4.915,"sigma_L":0.4647,"n":99},{"region":"Fairfield","mu_R":-0.045,"sigma_R":0.0324,"mu_L":6.3167,"sigma_L":0.423,"n":76},{"region":"Fairfield - East","mu_R":-0.0399,"sigma_R":0.0323,"mu_L":6.4801,"sigma_L":0.3972,"n":87},{"region":"Fairfield - West","mu_R":-0.0457,"sigma_R":0.028,"mu_L":6.1762,"sigma_L":0.4094,"n":207},{"region":"Five Dock - Abbotsford","mu_R":0.1059,"sigma_R":0.0469,"mu_L":6.1228,"sigma_L":0.3193,"n":122},{"region":"Forestville - Killarney Heights","mu_R":0.0715,"sigma_R":0.0262,"mu_L":6.5946,"sigma_L":0.2558,"n":122},{"region":"Frenchs Forest - Oxford Falls","mu_R":0.0672,"sigma_R":0.0262,"mu_L":6.6138,"sigma_L":0.3972,"n":161},{"region":"Freshwater - Brookvale","mu_R":0.1066,"sigma_R":0.0482,"mu_L":6.2651,"sigma_L":0.3441,"n":166},{"region":"Galston - Laughtondale","mu_R":0.0568,"sigma_R":0.0411,"mu_L":8.9764,"sigma_L":1.6015,"n":66},{"region":"Gladesville - Huntleys Point","mu_R":0.1129,"sigma_R":0.0562,"mu_L":6.4493,"sigma_L":0.3173,"n":96},{"region":"Glebe - Forest Lodge","mu_R":0.1171,"sigma_R":0.0606,"mu_L":5.1437,"sigma_L":0.5957,"n":107},{"region":"Gledswood Hills - Gregory Hills","mu_R":-0.0484,"sigma_R":0.0191,"mu_L":6.0742,"sigma_L":0.2527,"n":182},{"region":"Glendenning - Dean Park","mu_R":-0.0779,"sigma_R":0.0199,"mu_L":6.1291,"sigma_L":0.2271,"n":110},{"region":"Glenfield","mu_R":-0.0533,"sigma_R":0.0279,"mu_L":6.2174,"sigma_L":0.4834,"n":84},{"region":"Glenhaven","mu_R":0.0555,"sigma_R":0.0387,"mu_L":6.9345,"sigma_L":0.6317,"n":68},{"region":"Glenmore Park - Regentville","mu_R":-0.0517,"sigma_R":0.03,"mu_L":6.2266,"sigma_L":0.3236,"n":355},{"region":"Glenwood","mu_R":-0.012,"sigma_R":0.0245,"mu_L":6.1622,"sigma_L":0.2361,"n":166},{"region":"Gordon - Killara","mu_R":0.1324,"sigma_R":0.0465,"mu_L":6.9492,"sigma_L":0.3407,"n":198},{"region":"Granville - Clyde","mu_R":-0.0342,"sigma_R":0.0374,"mu_L":6.1178,"sigma_L":0.3987,"n":84},{"region":"Green Valley","mu_R":-0.054,"sigma_R":0.0333,"mu_L":6.2176,"sigma_L":0.3366,"n":90},{"region":"Greenacre - North","mu_R":-0.0135,"sigma_R":0.0296,"mu_L":6.2561,"sigma_L":0.3382,"n":233},{"region":"Greenacre - South","mu_R":-0.0077,"sigma_R":0.0343,"mu_L":6.0888,"sigma_L":0.2669,"n":12},{"region":"Greenfield Park - Prairiewood","mu_R":-0.0399,"sigma_R":0.0252,"mu_L":6.3654,"sigma_L":0.1316,"n":51},{"region":"Greenwich - Riverview","mu_R":0.1487,"sigma_R":0.0592,"mu_L":6.4917,"sigma_L":0.3589,"n":118},{"region":"Greystanes - South","mu_R":-0.0288,"sigma_R":0.0257,"mu_L":6.3365,"sigma_L":0.2172,"n":229},{"region":"Guildford - South Granville","mu_R":-0.0356,"sigma_R":0.0274,"mu_L":6.291,"sigma_L":0.3992,"n":209},{"region":"Guildford West - Merrylands West","mu_R":-0.0385,"sigma_R":0.0266,"mu_L":6.1854,"sigma_L":0.4325,"n":121},{"region":"Gymea - Grays Point","mu_R":0.0339,"sigma_R":0.0273,"mu_L":6.4527,"sigma_L":0.2615,"n":81},{"region":"Haberfield - Summer Hill","mu_R":0.1138,"sigma_R":0.0368,"mu_L":6.3359,"sigma_L":0.3242,"n":56},{"region":"Harrington Park","mu_R":-0.0211,"sigma_R":0.0307,"mu_L":6.4801,"sigma_L":0.2746,"n":174},{"region":"Hassall Grove - Plumpton","mu_R":-0.0781,"sigma_R":0.0188,"mu_L":6.291,"sigma_L":0.2474,"n":187},{"region":"Heathcote - Waterfall","mu_R":-0.0167,"sigma_R":0.0139,"mu_L":6.581,"sigma_L":0.135,"n":5},{"region":"Hinchinbrook","mu_R":-0.0471,"sigma_R":0.0395,"mu_L":6.1696,"sigma_L":0.339,"n":141},{"region":"Holsworthy - Wattle Grove","mu_R":-0.0304,"sigma_R":0.0298,"mu_L":6.2317,"sigma_L":0.3396,"n":190},{"region":"Homebush","mu_R":0.0916,"sigma_R":0.0445,"mu_L":6.4795,"sigma_L":0.2814,"n":29},{"region":"Hornsby - East","mu_R":0.0314,"sigma_R":0.031,"mu_L":6.7395,"sigma_L":0.3808,"n":126},{"region":"Horsley Park - Kemps Creek","mu_R":0.0685,"sigma_R":0.0286,"mu_L":9.2285,"sigma_L":0.146,"n":19},{"region":"Hoxton Park - Carnes Hill - Horningsea Park","mu_R":-0.0496,"sigma_R":0.0287,"mu_L":6.1634,"sigma_L":0.2958,"n":118},{"region":"Hunters Hill - Woolwich","mu_R":0.1701,"sigma_R":0.0563,"mu_L":6.5359,"sigma_L":0.3865,"n":107},{"region":"Hurstville - Central","mu_R":0.0613,"sigma_R":0.0416,"mu_L":6.2014,"sigma_L":0.2588,"n":128},{"region":"Illawong - Alfords Point","mu_R":0.016,"sigma_R":0.0162,"mu_L":6.5182,"sigma_L":0.1095,"n":6},{"region":"Ingleburn","mu_R":-0.065,"sigma_R":0.0345,"mu_L":6.2377,"sigma_L":0.5148,"n":216},{"region":"Jamisontown - South Penrith","mu_R":-0.0695,"sigma_R":0.0226,"mu_L":6.4889,"sigma_L":0.2682,"n":231},{"region":"Jordan Springs - Llandilo","mu_R":-0.0467,"sigma_R":0.0339,"mu_L":6.1875,"sigma_L":1.0573,"n":176},{"region":"Kellyville - East","mu_R":0.0177,"sigma_R":0.0482,"mu_L":6.3883,"sigma_L":0.6934,"n":503},{"region":"Kellyville Ridge - The Ponds","mu_R":-0.001,"sigma_R":0.0241,"mu_L":6.088,"sigma_L":0.242,"n":363},{"region":"Kensington (NSW)","mu_R":0.1391,"sigma_R":0.0485,"mu_L":6.1063,"sigma_L":0.403,"n":44},{"region":"Kingsford","mu_R":0.1244,"sigma_R":0.0393,"mu_L":6.0351,"sigma_L":0.2923,"n":76},{"region":"Kingsgrove (South) - Bardwell Park","mu_R":0.0419,"sigma_R":0.0278,"mu_L":6.2849,"sigma_L":0.2848,"n":44},{"region":"Kingsgrove - North","mu_R":0.0357,"sigma_R":0.0357,"mu_L":6.2022,"sigma_L":0.2784,"n":115},{"region":"Kingswood - Werrington","mu_R":-0.0588,"sigma_R":0.0607,"mu_L":6.4152,"sigma_L":0.7431,"n":114},{"region":"Kogarah","mu_R":0.0712,"sigma_R":0.0764,"mu_L":6.0289,"sigma_L":0.3303,"n":57},{"region":"Kogarah Bay - Carlton - Allawah","mu_R":0.0459,"sigma_R":0.0361,"mu_L":6.2051,"sigma_L":0.2839,"n":129},{"region":"Kurrajong Heights - Ebenezer","mu_R":-0.0234,"sigma_R":0.0557,"mu_L":8.3092,"sigma_L":1.7238,"n":330},{"region":"Lakemba","mu_R":-0.0109,"sigma_R":0.0297,"mu_L":6.1836,"sigma_L":0.3304,"n":25},{"region":"Lalor Park - Kings Langley","mu_R":-0.0477,"sigma_R":0.0329,"mu_L":6.4784,"sigma_L":0.1592,"n":233},{"region":"Lane Cove","mu_R":0.1161,"sigma_R":0.0351,"mu_L":6.4589,"sigma_L":0.355,"n":109},{"region":"Leichhardt","mu_R":0.0633,"sigma_R":0.0401,"mu_L":5.3871,"sigma_L":0.4049,"n":175},{"region":"Leppington - Catherine Field","mu_R":-0.0015,"sigma_R":0.1123,"mu_L":7.5364,"sigma_L":1.9733,"n":80},{"region":"Lethbridge Park - Tregear","mu_R":-0.1076,"sigma_R":0.0288,"mu_L":6.2114,"sigma_L":0.3282,"n":306},{"region":"Leumeah - Minto Heights","mu_R":-0.0859,"sigma_R":0.0238,"mu_L":6.4169,"sigma_L":0.419,"n":213},{"region":"Lidcombe","mu_R":0.0144,"sigma_R":0.0427,"mu_L":6.0948,"sigma_L":0.4432,"n":88},{"region":"Lilli Pilli - Port Hacking - Dolans Bay","mu_R":0.0629,"sigma_R":0.023,"mu_L":6.2424,"sigma_L":0.1566,"n":4},{"region":"Lilyfield - Rozelle","mu_R":0.0914,"sigma_R":0.0457,"mu_L":5.2713,"sigma_L":0.4325,"n":222},{"region":"Lindfield - Roseville","mu_R":0.1331,"sigma_R":0.0446,"mu_L":6.8172,"sigma_L":0.3094,"n":235},{"region":"Liverpool - East","mu_R":-0.0471,"sigma_R":0.0288,"mu_L":6.4111,"sigma_L":0.3304,"n":84},{"region":"Loftus - Yarrawarrah","mu_R":0.0006,"sigma_R":0.0186,"mu_L":6.4995,"sigma_L":0.2163,"n":9},{"region":"Lurnea - Cartwright","mu_R":-0.0659,"sigma_R":0.0253,"mu_L":6.4109,"sigma_L":0.2383,"n":109},{"region":"Macquarie Fields","mu_R":-0.0783,"sigma_R":0.0327,"mu_L":6.3919,"sigma_L":0.5079,"n":96},{"region":"Macquarie Park - Marsfield","mu_R":0.0774,"sigma_R":0.0195,"mu_L":6.3408,"sigma_L":0.2531,"n":43},{"region":"Malabar - La Perouse","mu_R":0.1224,"sigma_R":0.051,"mu_L":6.1769,"sigma_L":0.317,"n":60},{"region":"Manly - Fairlight","mu_R":0.1552,"sigma_R":0.0561,"mu_L":5.8207,"sigma_L":0.3691,"n":97},{"region":"Manly Vale - Allambie Heights","mu_R":0.0794,"sigma_R":0.0331,"mu_L":6.3942,"sigma_L":0.3176,"n":136},{"region":"Maroubra - South","mu_R":0.115,"sigma_R":0.0492,"mu_L":5.892,"sigma_L":0.3446,"n":186},{"region":"Marrickville - South","mu_R":0.059,"sigma_R":0.0391,"mu_L":5.6437,"sigma_L":0.4372,"n":160},{"region":"Marsden Park - Shanes Park","mu_R":-0.0645,"sigma_R":0.0513,"mu_L":5.5845,"sigma_L":0.727,"n":148},{"region":"Mascot","mu_R":0.0545,"sigma_R":0.0315,"mu_L":5.7656,"sigma_L":0.355,"n":52},{"region":"Matraville - Chifley","mu_R":0.0846,"sigma_R":0.0217,"mu_L":6.2811,"sigma_L":0.2246,"n":81},{"region":"Menai - Lucas Heights - Woronora","mu_R":0.0078,"sigma_R":0.0246,"mu_L":6.2652,"sigma_L":0.2883,"n":68},{"region":"Merrylands - Holroyd","mu_R":-0.0275,"sigma_R":0.034,"mu_L":6.2443,"sigma_L":0.3736,"n":186},{"region":"Minto - St Andrews","mu_R":-0.0776,"sigma_R":0.0273,"mu_L":6.3265,"sigma_L":0.3135,"n":276},{"region":"Miranda - Yowie Bay","mu_R":0.0341,"sigma_R":0.032,"mu_L":6.4966,"sigma_L":0.2694,"n":126},{"region":"Mona Vale - Warriewood (North)","mu_R":0.078,"sigma_R":0.036,"mu_L":6.4668,"sigma_L":0.4242,"n":69},{"region":"Monterey - Brighton-le-Sands - Kyeemagh","mu_R":0.0695,"sigma_R":0.0425,"mu_L":6.1982,"sigma_L":0.2896,"n":61},{"region":"Mortdale - Oatley","mu_R":0.0209,"sigma_R":0.0392,"mu_L":6.168,"sigma_L":0.3536,"n":77},{"region":"Mosman - South","mu_R":0.2107,"sigma_R":0.0663,"mu_L":6.2627,"sigma_L":0.4876,"n":302},{"region":"Mount Annan","mu_R":-0.0621,"sigma_R":0.0252,"mu_L":6.4008,"sigma_L":0.3051,"n":259},{"region":"Mount Druitt - Whalan","mu_R":-0.0914,"sigma_R":0.035,"mu_L":6.3958,"sigma_L":0.3574,"n":159},{"region":"Mulgoa - Luddenham - Orchard Hills","mu_R":-0.0114,"sigma_R":0.0642,"mu_L":7.6679,"sigma_L":1.4883,"n":54},{"region":"Narrabeen - Wheeler Heights","mu_R":0.0749,"sigma_R":0.0434,"mu_L":6.4612,"sigma_L":0.3372,"n":51},{"region":"Narwee - Beverly Hills","mu_R":0.0222,"sigma_R":0.0331,"mu_L":6.2418,"sigma_L":0.2459,"n":132},{"region":"Neutral Bay - Kirribilli","mu_R":0.2021,"sigma_R":0.0922,"mu_L":5.8287,"sigma_L":0.7022,"n":39},{"region":"Newport - Bilgola","mu_R":0.0741,"sigma_R":0.0377,"mu_L":6.5097,"sigma_L":0.289,"n":49},{"region":"Newtown (NSW)","mu_R":0.0692,"sigma_R":0.0514,"mu_L":4.9037,"sigma_L":0.3084,"n":158},{"region":"Normanhurst - Thornleigh - Westleigh","mu_R":0.0318,"sigma_R":0.0249,"mu_L":6.6184,"sigma_L":0.3585,"n":209},{"region":"North Kellyville","mu_R":-0.0564,"sigma_R":null,"mu_L":6.3276,"sigma_L":null,"n":1},{"region":"North Narrabeen - Warriewood (South)","mu_R":0.0653,"sigma_R":0.0264,"mu_L":6.1523,"sigma_L":0.6016,"n":119},{"region":"North Parramatta","mu_R":0.0021,"sigma_R":0.0356,"mu_L":6.2524,"sigma_L":0.3036,"n":62},{"region":"North Rocks","mu_R":0.0224,"sigma_R":0.0213,"mu_L":6.6385,"sigma_L":0.1546,"n":86},{"region":"North Ryde - East Ryde","mu_R":0.0684,"sigma_R":0.0289,"mu_L":6.3782,"sigma_L":0.275,"n":129},{"region":"North Sydney - Lavender Bay","mu_R":0.1667,"sigma_R":0.067,"mu_L":5.4159,"sigma_L":0.4356,"n":39},{"region":"Northmead","mu_R":0.0061,"sigma_R":0.0341,"mu_L":6.4024,"sigma_L":0.3188,"n":123},{"region":"Oatlands - Dundas Valley","mu_R":0.0294,"sigma_R":0.0315,"mu_L":6.4274,"sigma_L":0.4053,"n":179},{"region":"Oatley - Hurstville Grove","mu_R":0.0654,"sigma_R":0.0385,"mu_L":6.4076,"sigma_L":0.2892,"n":105},{"region":"Oran Park","mu_R":-0.0384,"sigma_R":0.022,"mu_L":6.1479,"sigma_L":0.1987,"n":136},{"region":"Oyster Bay - Como - Jannali","mu_R":0.0115,"sigma_R":0.0342,"mu_L":6.4773,"sigma_L":0.2649,"n":121},{"region":"Paddington - Moore Park","mu_R":0.1647,"sigma_R":0.0721,"mu_L":4.8579,"sigma_L":0.4598,"n":215},{"region":"Padstow","mu_R":0.0006,"sigma_R":0.0323,"mu_L":6.2372,"sigma_L":0.3967,"n":193},{"region":"Pagewood - Hillsdale - Daceyville","mu_R":0.0827,"sigma_R":0.031,"mu_L":6.2277,"sigma_L":0.2072,"n":59},{"region":"Panania (North) - Milperra","mu_R":-0.0197,"sigma_R":0.0183,"mu_L":6.3022,"sigma_L":0.2693,"n":45},{"region":"Panania (South) - Picnic Point","mu_R":-0.0013,"sigma_R":0.0301,"mu_L":6.1731,"sigma_L":0.4116,"n":387},{"region":"Peakhurst - Lugarno","mu_R":0.0217,"sigma_R":0.0375,"mu_L":6.4362,"sigma_L":0.3148,"n":200},{"region":"Pemulwuy - Greystanes (North)","mu_R":-0.0088,"sigma_R":0.0265,"mu_L":5.7723,"sigma_L":0.3062,"n":41},{"region":"Pendle Hill - Girraween","mu_R":-0.0239,"sigma_R":0.0322,"mu_L":6.2229,"sigma_L":0.4223,"n":93},{"region":"Pennant Hills - Cheltenham","mu_R":0.0644,"sigma_R":0.0336,"mu_L":6.8271,"sigma_L":0.3019,"n":202},{"region":"Penrith","mu_R":-0.0639,"sigma_R":0.0423,"mu_L":6.4506,"sigma_L":0.4134,"n":116},{"region":"Penshurst","mu_R":0.0337,"sigma_R":0.0441,"mu_L":6.2286,"sigma_L":0.3519,"n":63},{"region":"Petersham - Stanmore","mu_R":0.0795,"sigma_R":0.0421,"mu_L":5.4673,"sigma_L":0.4176,"n":124},{"region":"Picton - Tahmoor - Buxton","mu_R":-0.0649,"sigma_R":0.0526,"mu_L":7.4162,"sigma_L":1.3626,"n":282},{"region":"Pitt Town - McGraths Hill","mu_R":0.0098,"sigma_R":0.0655,"mu_L":8.0121,"sigma_L":1.8026,"n":132},{"region":"Potts Point - Woolloomooloo","mu_R":0.2342,"sigma_R":0.1106,"mu_L":5.2104,"sigma_L":0.8216,"n":5},{"region":"Prestons","mu_R":-0.0493,"sigma_R":0.0225,"mu_L":6.133,"sigma_L":0.2288,"n":150},{"region":"Punchbowl","mu_R":-0.0227,"sigma_R":0.0319,"mu_L":6.2524,"sigma_L":0.3622,"n":121},{"region":"Putney","mu_R":0.1028,"sigma_R":0.0421,"mu_L":6.4157,"sigma_L":0.2662,"n":53},{"region":"Pymble","mu_R":0.1059,"sigma_R":0.0476,"mu_L":6.9244,"sigma_L":0.3625,"n":207},{"region":"Pyrmont","mu_R":0.0728,"sigma_R":0.0325,"mu_L":4.5435,"sigma_L":0.1324,"n":5},{"region":"Quakers Hill","mu_R":-0.0475,"sigma_R":0.0218,"mu_L":6.2901,"sigma_L":0.2463,"n":279},{"region":"Randwick - North","mu_R":0.1468,"sigma_R":0.0466,"mu_L":5.7248,"sigma_L":0.4784,"n":137},{"region":"Redfern","mu_R":0.0885,"sigma_R":0.056,"mu_L":4.7631,"sigma_L":0.4063,"n":71},{"region":"Regents Park","mu_R":-0.024,"sigma_R":0.033,"mu_L":6.2831,"sigma_L":0.1643,"n":31},{"region":"Revesby","mu_R":-0.0066,"sigma_R":0.027,"mu_L":6.1646,"sigma_L":0.4248,"n":204},{"region":"Rhodes","mu_R":0.1743,"sigma_R":0.0706,"mu_L":6.3901,"sigma_L":0.3635,"n":9},{"region":"Richmond - Clarendon","mu_R":-0.0638,"sigma_R":0.0389,"mu_L":6.588,"sigma_L":0.7055,"n":178},{"region":"Riverstone","mu_R":-0.0393,"sigma_R":0.0864,"mu_L":6.7246,"sigma_L":1.2366,"n":168},{"region":"Riverwood","mu_R":0.0012,"sigma_R":0.0291,"mu_L":6.4081,"sigma_L":1.05,"n":79},{"region":"Rockdale - Banksia","mu_R":0.0231,"sigma_R":0.0327,"mu_L":6.0171,"sigma_L":0.3496,"n":75},{"region":"Rooty Hill - Minchinbury","mu_R":-0.0626,"sigma_R":0.0281,"mu_L":6.3398,"sigma_L":0.3026,"n":162},{"region":"Rose Bay - Vaucluse - Watsons Bay","mu_R":0.2292,"sigma_R":0.0723,"mu_L":6.3824,"sigma_L":0.4712,"n":194},{"region":"Rosebery - Beaconsfield","mu_R":0.0795,"sigma_R":0.0441,"mu_L":5.5662,"sigma_L":0.6475,"n":66},{"region":"Rosehill - Harris Park","mu_R":-0.0328,"sigma_R":0.0583,"mu_L":6.205,"sigma_L":0.4799,"n":14},{"region":"Roselands","mu_R":0.005,"sigma_R":0.0358,"mu_L":6.2125,"sigma_L":0.3138,"n":123},{"region":"Rosemeadow - Glen Alpine","mu_R":-0.0735,"sigma_R":0.0409,"mu_L":6.5358,"sigma_L":0.4113,"n":242},{"region":"Rouse Hill - Beaumont Hills","mu_R":0.0024,"sigma_R":0.0527,"mu_L":6.3082,"sigma_L":0.6641,"n":248},{"region":"Ryde - North","mu_R":0.0656,"sigma_R":0.0351,"mu_L":6.4407,"sigma_L":0.348,"n":193},{"region":"Sans Souci - Ramsgate","mu_R":0.0769,"sigma_R":0.0457,"mu_L":6.26,"sigma_L":0.3325,"n":107},{"region":"Schofields (West) - Colebee","mu_R":-0.0229,"sigma_R":0.0545,"mu_L":6.2891,"sigma_L":0.7123,"n":37},{"region":"Schofields - East","mu_R":-0.0321,"sigma_R":0.0926,"mu_L":6.5961,"sigma_L":1.3352,"n":158},{"region":"Seven Hills - Prospect","mu_R":-0.0479,"sigma_R":0.0262,"mu_L":6.4018,"sigma_L":0.2594,"n":275},{"region":"Silverwater - Newington","mu_R":0.0488,"sigma_R":0.0174,"mu_L":5.6691,"sigma_L":0.212,"n":46},{"region":"Singleton","mu_R":0.0853,"sigma_R":0.0578,"mu_L":4.7171,"sigma_L":0.4339,"n":27},{"region":"Smithfield - Wetherill Park","mu_R":-0.0458,"sigma_R":0.0279,"mu_L":6.3808,"sigma_L":0.3014,"n":156},{"region":"South Coogee","mu_R":0.1534,"sigma_R":0.0558,"mu_L":6.0911,"sigma_L":0.3127,"n":47},{"region":"South Hurstville - Blakehurst","mu_R":0.0618,"sigma_R":0.0445,"mu_L":6.4415,"sigma_L":0.3763,"n":112},{"region":"South Wentworthville","mu_R":-0.0269,"sigma_R":0.0344,"mu_L":6.3305,"sigma_L":0.4284,"n":57},{"region":"Spring Farm","mu_R":-0.0616,"sigma_R":0.0179,"mu_L":6.087,"sigma_L":0.2301,"n":123},{"region":"St Clair","mu_R":-0.0655,"sigma_R":0.0228,"mu_L":6.4403,"sigma_L":0.3532,"n":229},{"region":"St Ives","mu_R":0.0967,"sigma_R":0.0365,"mu_L":6.9168,"sigma_L":0.3509,"n":293},{"region":"St Johns Park - Wakeley","mu_R":-0.0404,"sigma_R":0.0291,"mu_L":6.3383,"sigma_L":0.2177,"n":68},{"region":"St Leonards - Naremburn","mu_R":0.1342,"sigma_R":0.0453,"mu_L":5.9023,"sigma_L":0.3706,"n":58},{"region":"St Marys - North St Marys","mu_R":-0.081,"sigma_R":0.0424,"mu_L":6.5052,"sigma_L":0.3457,"n":198},{"region":"Stanhope Gardens - Parklea","mu_R":-0.0197,"sigma_R":0.0253,"mu_L":6.0782,"sigma_L":0.2455,"n":152},{"region":"Strathfield - East","mu_R":0.142,"sigma_R":0.0516,"mu_L":6.5248,"sigma_L":0.4991,"n":163},{"region":"Strathfield South","mu_R":0.0534,"sigma_R":0.0313,"mu_L":6.1555,"sigma_L":0.178,"n":18},{"region":"Surry Hills","mu_R":0.1103,"sigma_R":0.0676,"mu_L":4.5873,"sigma_L":0.361,"n":70},{"region":"Sutherland - Kirrawee","mu_R":0.0164,"sigma_R":0.026,"mu_L":6.4776,"sigma_L":0.2411,"n":114},{"region":"Sydenham - Tempe - St Peters","mu_R":0.0307,"sigma_R":0.0365,"mu_L":5.3887,"sigma_L":0.4119,"n":108},{"region":"Sydney (North) - Millers Point","mu_R":0.1965,"sigma_R":0.0634,"mu_L":4.9398,"sigma_L":0.3805,"n":74},{"region":"Sylvania - Taren Point","mu_R":0.0697,"sigma_R":0.0576,"mu_L":6.4812,"sigma_L":0.21,"n":109},{"region":"Terrey Hills - Duffys Forest","mu_R":0.0915,"sigma_R":0.0556,"mu_L":7.604,"sigma_L":1.5118,"n":42},{"region":"The Oaks - Oakdale","mu_R":-0.0264,"sigma_R":0.054,"mu_L":8.8421,"sigma_L":1.9649,"n":102},{"region":"Toongabbie - Constitution Hill","mu_R":-0.0256,"sigma_R":0.025,"mu_L":6.3906,"sigma_L":0.3423,"n":59},{"region":"Toongabbie - West","mu_R":-0.0273,"sigma_R":0.0344,"mu_L":6.4375,"sigma_L":0.3675,"n":129},{"region":"Turramurra","mu_R":0.0906,"sigma_R":0.0477,"mu_L":6.9468,"sigma_L":0.3196,"n":257},{"region":"Ultimo","mu_R":0.1116,"sigma_R":0.0543,"mu_L":4.5913,"sigma_L":0.4828,"n":10},{"region":"Wahroonga (East) - Warrawee","mu_R":0.0958,"sigma_R":0.0559,"mu_L":6.9264,"sigma_L":0.44,"n":264},{"region":"Wahroonga (West) - Waitara","mu_R":0.066,"sigma_R":0.0262,"mu_L":6.6764,"sigma_L":0.2962,"n":7},{"region":"Wangi Wangi - Rathmines","mu_R":-0.0669,"sigma_R":0.0133,"mu_L":7.7322,"sigma_L":0.5166,"n":5},{"region":"Warragamba - Silverdale","mu_R":-0.0804,"sigma_R":0.051,"mu_L":6.8175,"sigma_L":1.1191,"n":54},{"region":"Warwick Farm","mu_R":-0.0629,"sigma_R":0.0362,"mu_L":6.454,"sigma_L":0.0985,"n":11},{"region":"Waterloo","mu_R":0.0377,"sigma_R":0.0351,"mu_L":4.7539,"sigma_L":0.236,"n":9},{"region":"Wentworthville - Westmead","mu_R":-0.011,"sigma_R":0.0318,"mu_L":6.3986,"sigma_L":0.3479,"n":83},{"region":"West Hoxton - Middleton Grange","mu_R":-0.0353,"sigma_R":0.0308,"mu_L":6.1279,"sigma_L":0.3036,"n":166},{"region":"West Pennant Hills","mu_R":0.065,"sigma_R":0.0397,"mu_L":6.8013,"sigma_L":0.356,"n":186},{"region":"West Ryde - Meadowbank","mu_R":0.0641,"sigma_R":0.0349,"mu_L":6.4667,"sigma_L":0.3232,"n":96},{"region":"Wiley Park","mu_R":-0.0244,"sigma_R":0.0241,"mu_L":6.1955,"sigma_L":0.3632,"n":24},{"region":"Willoughby","mu_R":0.1326,"sigma_R":0.0348,"mu_L":6.1691,"sigma_L":0.3717,"n":143},{"region":"Windsor - Bligh Park","mu_R":-0.0737,"sigma_R":0.0311,"mu_L":6.4819,"sigma_L":0.5547,"n":170},{"region":"Winston Hills","mu_R":-0.0041,"sigma_R":0.0206,"mu_L":6.4342,"sigma_L":0.2112,"n":136},{"region":"Woollahra","mu_R":0.211,"sigma_R":0.072,"mu_L":5.4533,"sigma_L":0.6709,"n":90},{"region":"Woolooware - Burraneer","mu_R":0.0743,"sigma_R":0.0308,"mu_L":6.4128,"sigma_L":0.3385,"n":39},{"region":"Yagoona - Birrong","mu_R":-0.0275,"sigma_R":0.0272,"mu_L":6.3165,"sigma_L":0.298,"n":200},{"region":"Yarramundi - Londonderry","mu_R":-0.0006,"sigma_R":0.056,"mu_L":8.8322,"sigma_L":1.5445,"n":56},{"region":"Zetland","mu_R":0.0916,"sigma_R":0.0297,"mu_L":5.1997,"sigma_L":0.3065,"n":14}]